livesettings/__init__.py
livesettings/admin.py
livesettings/apps.py
livesettings/conf.py
livesettings/fields.py
livesettings/forms.py
livesettings/models.py
livesettings/settings.py
livesettings/types.py
livesettings/migrations/0001_initial.py
livesettings/migrations/__init__.py
livesettings/templatetags/__init__.py
livesettings/templatetags/livesettings_tags.py
django_fs_livesettings-1.0.0.dist-info/LICENSE
django_fs_livesettings-1.0.0.dist-info/METADATA
django_fs_livesettings-1.0.0.dist-info/WHEEL
django_fs_livesettings-1.0.0.dist-info/top_level.txt
django_fs_livesettings-1.0.0.dist-info/RECORD
